Workbook

Sheet CL 2025 (Original)
A2: Financial Highlights (Unaudited) (in Canadian $ Million) | B2: 2025 | C2: 2024
A3: Summary of net earnings attributable to:
A4: Participating account | B4: 42 | C4: 107
A5: Common shareholder | B5: 2724 | C5: 3140
A6: Net earnings | B6: 2766 | C6: 3247
A8: Insurance service result | B8: 3450 | C8: 3258
A9: Net investment result | B9: 603 | C9: 1015
A10: Fee and other income | B10: 3016 | C10: 2853
A12: Total assets | B12: 505652 | C12: 461204
A13: Total assets under management or advisement | B13: 529301 | C13: 469722
A14: Total assets under administration | B14: 723435 | C14: 654853
A15: Total contractual service margin (net of reinsurance held) | B15: 13494 | C15: 13243
A17: Participating account surplus | B17: 3082 | C17: 3043
A18: Non-controlling interests | B18: – | C18: 10
A19: Shareholders’ equity | B19: 20938 | C19: 20909
A20: Total equity | B20: 24020 | C20: 23962
A21: LICAT Ratio | B21: 1.28 | C21: 1.3
A24: Consolidated Statements Of Earnings (in Canadian $ Million) | B24: 2025 | C24: 2024
A25: Insurance service result
A26: Insurance revenue | B26: 22131 | C26: 21007
A27: Insurance service expenses | B27: -17002 | C27: -16165
A28: Net expense from reinsurance contracts | B28: -1679 | C28: -1584
B29: 3450 | C29: 3258
A30: Net investment result (note 6)
A31: Net investment income | B31: 5837 | C31: 5719
A32: Changes in fair value on fair value through profit or loss assets | B32: 1328 | C32: 1280
B33: 7165 | C33: 6999
A34: Net finance income (expenses) from insurance contracts | B34: -6116 | C34: -5851
A35: Net finance income (expenses) from reinsurance contracts | B35: -303 | C35: 26
A36: Changes in investment contract liabilities | B36: -143 | C36: -159
B37: 603 | C37: 1015
A38: Net investment result - insurance contracts on account of segregated fund policyholders
A39: Net investment income | B39: 5044 | C39: 6828
A40: Net finance income (expenses) from insurance contracts | B40: -5044 | C40: -6828
B41: — | C41: —
A42: Other income and expenses
A43: Fee and other income | B43: 3016 | C43: 2853
A44: Operating and administrative expenses | B44: -3408 | C44: -3088
A45: Amortization of finite life intangible assets (note 9) | B45: -194 | C45: -185
A46: Financing costs (note 19) | B46: -107 | C46: -105
A47: Restructuring and integration expenses (note 4) | B47: -346 | C47: -49
A48: Earnings before income taxes | B48: 3014 | C48: 3699
A49: Income taxes (note 29) | B49: 248 | C49: 455
A50: Net earnings before non-controlling interests | B50: 2766 | C50: 3244
A51: Attributable to non-controlling interests (note 22) | B51: — | C51: -3
A52: Net earnings | B52: 2766 | C52: 3247
A53: Net earnings - participating account (note 21) | B53: 42 | C53: 107
A54: Net earnings - common shareholder | B54: 2724 | C54: 3140
A58: Consolidated Balance Sheet (in Canadian $ Million) | B58: 2025 | C58: 2024
A59: Assets
A60: Cash and cash equivalents | B60: 4679 | C60: 4522
A61: Bonds (note 6) | B61: 104567 | C61: 100863
A62: Mortgage loans (note 6) | B62: 26009 | C62: 25477
A63: Stocks (note 6) | B63: 16990 | C63: 14794
A64: Investment properties (note 6) | B64: 8277 | C64: 8235
B65: 160522 | C65: 153891
A67: Insurance contract assets (note 14) | B67: 1256 | C67: 858
A68: Reinsurance contract held assets (note 15) | B68: 6399 | C68: 6544
A69: Goodwill (note 9) | B69: 6905 | C69: 6827
A70: Intangible assets (note 9) | B70: 2983 | C70: 2866
A71: Derivative financial instruments (note 30) | B71: 1290 | C71: 1458
A72: Owner occupied properties (note 10) | B72: 641 | C72: 589
A73: Fixed assets (note 10) | B73: 321 | C73: 277
A74: Accounts and interest receivable | B74: 3926 | C74: 3704
A75: Other assets (note 11) | B75: 2981 | C75: 2647
A76: Current income taxes | B76: 315 | C76: 185
A77: Deferred tax assets (note 29) | B77: 1156 | C77: 958
A78: Investments on account of segregated fund policyholders (note 17) | B78: 316957 | C78: 280400
A79: Total assets | B79: 505652 | C79: 461204
A81: Liabilities
A82: Insurance contract liabilities (note 14) | B82: 147329 | C82: 140310
A83: Investment contract liabilities (note 16) | B83: 4422 | C83: 4687
A84: Reinsurance contract held liabilities (note 15) | B84: 787 | C84: 628
A85: Debentures and other debt instruments | B85: 827 | C85: 807
A86: Preferred shares (note 23) | B86: 1000 | C86: 1000
A87: Derivative financial instruments (note 30) | B87: 2130 | C87: 2074
A88: Accounts payable | B88: 2236 | C88: 2028
A89: Other liabilities (note 20) | B89: 5006 | C89: 4534
A90: Current income taxes | B90: 400 | C90: 227
A91: Deferred tax liabilities (note 29) | B91: 538 | C91: 547
A92: Insurance contracts on account of segregated fund policyholders (note 17) | B92: 56153 | C92: 51934
A93: Investment contracts on account of segregated fund policyholders (note 17) | B93: 260804 | C93: 228466
A94: Total liabilities | B94: 481632 | C94: 437242
A96: Equity
A97: Participating account surplus (note 21) | B97: 3082 | C97: 3043
A98: Non-controlling interests (note 22) | B98: — | C98: 10
A99: Shareholder's equity
A100: Share capital
A101: Common shares (note 23) | B101: 7995 | C101: 7995
A102: Accumulated surplus | B102: 11332 | C102: 11758
A103: Accumulated other comprehensive income (note 27) | B103: 1154 | C103: 711
A104: Contributed surplus | B104: 457 | C104: 445
A105: Total equity | B105: 24020 | C105: 23962
A106: Total liabilities and equity | B106: 505652 | C106: 461204
A109: Consolidated Statements of Change in Equity | B109: Share Capital | C109: Contributed Surplus | D109: Accumulated Surplus | E109: Accumulated Other Comprehensive Income | F109: Total Shareholder's Equity | G109: Non-controlling Interest | H109: Participating Account Surplus | I109: Total Equity
A110: Balance, beginning of year | B110: 7995 | C110: 445 | D110: 11758 | E110: 711 | F110: 20909 | G110: 10 | H110: 3043 | I110: 23962
A111: Net Earnings | B111: — | C111: — | D111: 2724 | E111: — | F111: 2724 | G111: — | H111: 42 | I111: 2766
A112: Other comprehensive income (loss) | B112: — | C112: — | D112: — | E112: 443 | F112: 443 | G112: — | H112: -3 | I112: 440
B113: 7995 | C113: 445 | D113: 14482 | E113: 1154 | F113: 24076 | G113: 10 | H113: 3082 | I113: 27168
A114: Dividends to common shareholder | B114: — | C114: — | D114: -3150 | E114: — | F114: -3150 | G114: — | H114: — | I114: -3150
...

Sheet CL 2024 (Original)
A2: Financial Highlights (in Canadian $ millions) | B2: 2024 | C2: 2023
A3: Summary of net earnings attributable to:
A4: Participating account | B4: 107 | C4: 24
A5: Common shareholder | B5: 3140 | C5: 2394
A6: Net earnings | B6: 3247 | C6: 2418
A8: Insurance service result | B8: 3258 | C8: 3002
A9: Net investment result | B9: 1015 | C9: 200
A10: Fee and other income | B10: 2853 | C10: 2163
A12: Total assets | B12: 461204 | C12: 410616
A13: Total assets under management | B13: 576201 | C13: 499941
A14: Total assets under administration | B14: 654853 | C14: 567652
A15: Total contractual service margin (net of reinsurance held) | B15: 13243 | C15: 12458
A17: Participating account surplus | B17: 3043 | C17: 2844
A18: Non-controlling interests | B18: 10 | C18: 16
... A21: LICAT Ratio | B21: 1.3 | C21: 1.28
A24: Consolidated Statements of Earnings (in Canadian $ millions) | B24: 2024 | C24: 2023
A25: Insurance service result
A26: Insurance revenue | B26: 21007 | C26: 20188
A27: Insurance service expenses | B27: -16165 | C27: -15622
A28: Net expense from reinsurance contracts | B28: -1584 | C28: -1564
B29: 3258 | C29: 3002
A30: Net investment result (note 6)
A31: Net investment income | B31: 5719 | C31: 4877
A32: Changes in fair value on fair value through profit or loss assets | B32: 1280 | C32: 4267
B33: 6999 | C33: 9144
A34: Net finance income (expenses) from insurance contracts | B34: -5851 | C34: -9032
A35: Net finance income (expenses) from reinsurance contracts | B35: 26 | C35: 266
A36: Changes in investment contract liabilities | B36: -159 | C36: -178
B37: 1015 | C37: 200
A38: Net investment result - insurance contracts on account of segregated fund policyholders
A39: Net investment income (loss) | B39: 6828 | C39: 4808
A40: Net finance income (expenses) from insurance contracts | B40: -6828 | C40: -4808
B41: — | C41: —
A42: Other income and expenses
A43: Fee and other income | B43: 2853 | C43: 2163
A44: Operating and administrative expenses | B44: -3088 | C44: -2635
A45: Amortization of finite life intangible assets (note 9) | B45: -185 | C45: -160
A46: Financing costs (note 19) | B46: -105 | C46: -105
A47: Restructuring expenses (note 4) | B47: -49 | C47: -126
A48: Earnings before income taxes | B48: 3699 | C48: 2339
A49: Income taxes (note 29) | B49: 455 | C49: -80
A50: Net earnings before non-controlling interests | B50: 3244 | C50: 2419
A51: Attributable to non-controlling interests (note 22) | B51: -3 | C51: 1
A52: Net earnings | B52: 3247 | C52: 2418
A53: Net earnings - participating account (note 21) | B53: 107 | C53: 24
A54: Net earnings - common shareholder | B54: 3140 | C54: 2394
A57: Consolidated Balance Sheet (in Canadian $ millions) | B57: 2024 | C57: 2023
A58: Assets
A59: Cash and cash equivalents | B59: 4522 | C59: 3944
A60: Bonds (note 6) | B60: 100863 | C60: 91904
A61: Mortgage loans (note 6) | B61: 25477 | C61: 24449
A62: Stocks (note 6) | B62: 14794 | C62: 13589
A63: Investment properties (note 6) | B63: 8235 | C63: 7849
B64: 153891 | C64: 141735
A65: Insurance contract assets (note 14) | B65: 858 | C65: 902
A66: Reinsurance contract held assets (note 15) | B66: 6544 | C66: 6546
A67: Goodwill (note 9) | B67: 6827 | C67: 7072
A68: Intangible assets (note 9) | B68: 2866 | C68: 2484
A69: Derivative financial instruments (note 30) | B69: 1458 | C69: 1486
A70: Owner occupied properties (note 10) | B70: 589 | C70: 544
A71: Fixed assets (note 10) | B71: 277 | C71: 252
A72: Accounts and interest receivable | B72: 3704 | C72: 3117
A73: Other assets (note 11) | B73: 2647 | C73: 2344
A74: Current income taxes | B74: 185 | C74: 144
A75: Deferred tax assets (note 29) | B75: 958 | C75: 804
A76: Investments on account of segregated fund policyholders (note 17) | B76: 280400 | C76: 243186
A77: Total assets | B77: 461204 | C77: 410616
A79: Liabilities
A80: Insurance contract liabilities (note 14) | B80: 140310 | C80: 129689
A81: Investment contract liabilities (note 16) | B81: 4687 | C81: 4953
A82: Reinsurance contract held liabilities (note 15) | B82: 628 | C82: 475
A83: Debentures and other debt instruments | B83: 807 | C83: 748
A84: Preferred shares (note 23) | B84: 1000 | C84: 1000
A85: Derivative financial instruments (note 30) | B85: 2074 | C85: 1208
A86: Accounts payable | B86: 2028 | C86: 1672
A87: Other liabilities (note 20) | B87: 4534 | C87: 4401
A88: Current income taxes | B88: 227 | C88: 97
A89: Deferred tax liabilities (note 29) | B89: 547 | C89: 514
A90: Insurance contracts on account of segregated fund policyholders (note 17) | B90: 51934 | C90: 47410
A91: Investment contracts on account of segregated fund policyholders (note 17) | B91: 228466 | C91: 195776
A92: Total liabilities | B92: 437242 | C92: 387943
A94: Equity
A95: Participating account surplus (note 21) | B95: 3043 | C95: 2844
A96: Non-controlling interests (note 22) | B96: 10 | C96: 16
A97: Shareholder's equity
A98: Share capital
A99: Common shares (note 23) | B99: 7995 | C99: 7995
A100: Accumulated surplus | B100: 11758 | C100: 11456
A101: Accumulated other comprehensive income (loss) (note 27) | B101: 711 | C101: -71
A102: Contributed surplus | B102: 445 | C102: 433
A103: Total equity | B103: 23962 | C103: 22673
A104: Total liabilities and equity | B104: 461204 | C104: 410616
A107: Consolidated Statements of Changes in Equity (in Canadian $ millions) | B107: Share capital | C107: Contributed surplus | D107: Accumulated surplus | E107: Accumulated other comprehensive income (loss) | F107: Total shareholder's equity | G107: Non-controlling interests | H107: Participating account surplus | I107: Total equity
A108: Balance, beginning of year | B108: 7995 | C108: 433 | D108: 11456 | E108: (71) $ | F108: 19813 | G108: 16 | H108: 2844 | I108: 22673
A109: Net earnings (loss) | B109: — | C109: — | D109: 3140 | E109: — | F109: 3140 | G109: -3 | H109: 107 | I109: 3244
A110: Other comprehensive income | B110: — | C110: — | D110: — | E110: 782 | F110: 782 | G110: — | H110: 92 | I110: 874
B111: 7995 | C111: 433 | D111: 14596 | E111: 711 | F111: 23735 | G111: 13 | H111: 3043 | I111: 26791
A112: Dividends to common shareholder | B112: — | C112: — | D112: -2838 | E112: — | F112: -2838 | G112: — | H112: — | I112: -2838
A113: Share-based payments (note 25) | B113: — | C113: 12 | D113: — | E113: — | F113: 12 | G113: — | H113: — | I113: 12
A114: Derecognition of non-controlling interest in subsidiary | B114: — | C114: — | D114: — | E114: — | F114: — | G114: -3 | H114: — | I114: -3
...

Sheet CL 2023 (Original)
A2: Financial Highlights (unaudited) (in Canadian $ millions) | B2: 2023 | C2: 2022
A3: Summary of net earnings attributable to:
A4: Participating account | B4: 24 | C4: -91
A5: Common shareholder | B5: 2394 | C5: 3377
A6: Net earnings | B6: 2418 | C6: 3286
A8: Insurance service result | B8: 3002 | C8: 2766
A9: Net investment result | B9: 200 | C9: 1464
A10: Fee and other income | B10: 2163 | C10: 1932
A12: Total assets | B12: 410616 | C12: 378654
A13: Total assets under management | B13: 499941 | C13: 444064
A14: Total assets under administration | B14: 567652 | C14: 481753
A15: Total contractual service margin (net of reinsurance held) | B15: 12458 | C15: 12496
A17: Participating account surplus | B17: 2844 | C17: 2733
A18: Non-controlling interests | B18: 16 | C18: 51
... A20: Total equity | B20: 22673 | C20: 22788
A21: LICAT Ratio | B21: 1.28 | C21: ='CL 2022 (Original)'!B26 -> 1.2
A23: Consolidated Statements of Earnings (in Canadian $ millions) | B23: 2023 | C23: 2022
C24: (Restated)
A25: Insurance service result
A26: Insurance revenue | B26: 20188 | C26: 19424
A27: Insurance service expenses | B27: -15622 | C27: -15110
A28: Net expense from reinsurance contracts | B28: -1564 | C28: -1548
B29: 3002 | C29: 2766
A30: Net investment result (note 6)
A31: Net investment income | B31: 4877 | C31: 4599
A32: Changes in fair value on fair value through profit or loss assets | B32: 4267 | C32: -20289
B33: 9144 | C33: -15690
A34: Net finance income (expenses) from insurance contracts | B34: -9032 | C34: 18201
A35: Net finance income (expenses) from reinsurance contracts | B35: 266 | C35: -1261
A36: Changes in investment contract liabilities | B36: -178 | C36: 214
B37: 200 | C37: 1464
A38: Net investment result - insurance contracts on account of segregated fund policyholders
A39: Net investment income (loss) | B39: 4808 | C39: -4130
A40: Net finance income (expenses) from insurance contracts | B40: -4808 | C40: 4130
B41: — | C41: —
A42: Other income and expenses
A43: Fee and other income | B43: 2163 | C43: 1932
A44: Operating and administrative expenses | B44: -2635 | C44: -2221
A45: Amortization of finite life intangible assets (note 9) | B45: -160 | C45: -173
A46: Financing costs (note 19) | B46: -105 | C46: -104
A47: Restructuring expenses (note 4) | B47: -126 | C47: —
A48: Earnings before income taxes | B48: 2339 | C48: 3664
A49: Income taxes (note 29) | B49: -80 | C49: 375
A50: Net earnings before non-controlling interests | B50: 2419 | C50: 3289
A51: Attributable to non-controlling interests (note 22) | B51: 1 | C51: 3
A52: Net earnings | B52: 2418 | C52: 3286
A53: Net earnings (loss) - participating account (note 21) | B53: 24 | C53: -91
A54: Net earnings - common shareholder | B54: 2394 | C54: 3377
A57: Consolidated Balance Sheets (in Canadian $ millions) | B57: 2023 | C57: 2022 | D57: 2021
C58: (Restated) | D58: (Restated)
A59: Assets
A60: Cash and cash equivalents | B60: 3944 | C60: 3761 | D60: 3271
A61: Bonds (note 6) | B61: 91904 | C61: 85947 | D61: 103172
A62: Mortgage loans (note 6) | B62: 24449 | C62: 22843 | D62: 23540
A63: Stocks (note 6) | B63: 13589 | C63: 12679 | D63: 13268
A64: Investment properties (note 6) | B64: 7849 | C64: 8315 | D64: 7759
B65: 141735 | C65: 133545 | D65: 151010
A67: Insurance contract assets (note 14) | B67: 902 | C67: 886 | D67: 1311
A68: Reinsurance contract held assets (note 15) | B68: 6546 | C68: 6709 | D68: 9056
A69: Goodwill (note 9) | B69: 7072 | C69: 6372 | D69: 6408
A70: Intangible assets (note 9) | B70: 2484 | C70: 2470 | D70: 2362
A71: Derivative financial instruments (note 30) | B71: 1486 | C71: 1120 | D71: 582
A72: Owner occupied properties (note 10) | B72: 544 | C72: 532 | D72: 552
A73: Fixed assets (note 10) | B73: 252 | C73: 257 | D73: 288
A74: Accounts and interest receivable | B74: 3117 | C74: 2312 | D74: 2064
A75: Other assets (note 11) | B75: 2344 | C75: 2108 | D75: 1836
A76: Current income taxes | B76: 144 | C76: 256 | D76: 242
A77: Deferred tax assets (note 29) | B77: 804 | C77: 479 | D77: 478
A78: Investments on account of segregated fund policyholders (note 17) | B78: 243186 | C78: 221608 | D78: 240500
A79: Total assets | B79: 410616 | C79: 378654 | D79: 416689
A81: Liabilities
A82: Insurance contract liabilities (note 14) | B82: 129689 | C82: 120503 | D82: 140639
A83: Investment contract liabilities (note 16) | B83: 4953 | C83: 4672 | D83: 4520
A84: Reinsurance contract held liabilities (note 15) | B84: 475 | C84: 326 | D84: 986
A85: Debentures and other debt instruments | B85: 748 | C85: 747 | D85: 745
A86: Preferred shares (note 23) | B86: 1000 | C86: 1000 | D86: 1000
A87: Derivative financial instruments (note 30) | B87: 1208 | C87: 1575 | D87: 1005
A88: Accounts payable | B88: 1672 | C88: 1612 | D88: 1385
A89: Other liabilities (note 20) | B89: 4401 | C89: 3070 | D89: 3400
A90: Current income taxes | B90: 97 | C90: 52 | D90: 160
A91: Deferred tax liabilities (note 29) | B91: 514 | C91: 701 | D91: 619
A92: Insurance contracts on account of segregated fund policyholders (note 17) | B92: 47410 | C92: 45409 | D92: 50831
A93: Investment contracts on account of segregated fund policyholders (note 17) | B93: 195776 | C93: 176199 | D93: 189669
A94: Total liabilities | B94: 387943 | C94: 355866 | D94: 394959
A95: Equity
A96: Participating account surplus (note 21) | B96: 2844 | C96: 2733 | D96: 2985
A97: Non-controlling interests (note 22) | B97: 16 | C97: 51 | D97: 26
A98: Shareholders' equity
A99: Share capital
A100: Common shares (note 23) | B100: 7995 | C100: 7884 | D100: 7884
A101: Accumulated surplus | B101: 11456 | C101: 12054 | D101: 10439
A102: Accumulated other comprehensive loss (note 27) | B102: -71 | C102: -359 | D102: -23
A103: Contributed surplus | B103: 433 | C103: 425 | D103: 419
A104: Total equity | B104: 22673 | C104: 22788 | D104: 21730
A105: Total liabilities and equity | B105: 410616 | C105: 378654 | D105: 416689
A108: Consolidated Statements of Changes in Equity (in Canadian $ millions) | B108: Share capital | C108: Contributed surplus | D108: Accumulated surplus | E108: Accumulated other comprehensive income (loss) | F108: Total shareholders' equity | G108: Non-controlling interests | H108: Participating account surplus | I108: Total equity
A109: Balance, beginning of year (restated) | B109: 7884 | C109: 425 | D109: 12054 | E109: (359) $ | F109: 20004 | G109: 51 | H109: 2733 | I109: 22788
A110: Impact of initial application of IFRS 9 (note 3) | B110: — | C110: — | D110: -31 | E110: — | F110: -31 | G110: — | H110: — | I110: -31
A111: Revised balance, beginning of year | B111: 7884 | C111: 425 | D111: 12023 | E111: -359 | F111: 19973 | G111: 51 | H111: 2733 | I111: 22757
A112: Net earnings | B112: — | C112: — | D112: 2394 | E112: — | F112: 2394 | G112: 1 | H112: 24 | I112: 2419
...

Sheet CL 2022 (Original)
A2: Financial Highlight (unaudited) (in Canadian $ millions) | B2: 2022 | C2: 2021
A3: Summary of net earnings attribute to:
A4: Participating account
A5: Net earnings before policyholder dividend | B5: 1809 | C5: 1708
A6: Policyholder dividends | B6: 1625 | C6: 1405
A7: Net earnings – participating account | B7: 184 | C7: 303
A8: Common shareholder | B8: 2995 | C8: 2868
A9: Net earnings | B9: 3179 | C9: 3171
A11: Total net premiums | B11: 54322 | C11: 50609
A12: Total premiums and deposits | B12: 98025 | C12: 94160
A13: Fee and other income | B13: 3325 | C13: 3414
A14: Net policyholder benefits, dividends and experience refunds | B14: 48246 | C14: 42319
A15: Total assets | B15: 393982 | C15: 426404
A16: Proprietary mutual funds and institutional assets | B16: 65410 | C16: 77019
A17: Total assets under management | B17: 459392 | C17: 503423
... A26: LICAT Ratio | B26: 1.2 | C26: 1.24
A29: Consolidated Statements of Earnings (in Canadian $ millions) | B29: 2022 | C29: 2021
A30: Income
A31: Premium income
A32: Gross premiums written | B32: 58060 | C32: 54340
A33: Ceded premiums | B33: -3738 | C33: -3731
A34: Total net premiums | B34: 54322 | C34: 50609
A35: Net investment income (note 6)
A36: Regular net investment income | B36: -4898 | C36: 4502
A37: Changes in fair value through profit or loss | B37: -16011 | C37: -1240
A38: Total net investment income (loss) | B38: -11113 | C38: 3262
A39: Fee and other income | B39: -3325 | C39: 3414
B40: 46534 | C40: 57285
A41: Benefits and expenses
A42: Policyholder benefits
A43: Gross | B43: 48611 | C43: 43401
A44: Ceded | B44: -2537 | C44: -2505
A45: Total net policyholder benefits | B45: 46074 | C45: 40896
A46: Changes in insurance and investment contract liabilities
A47: Gross | B47: -12410 | C47: 4394
A48: Ceded | B48: 1169 | C48: 1081
A49: Total net changes in insurance and investment contract liabilities | B49: -11241 | C49: 5475
A50: Policyholder dividends and experience refunds | B50: 2172 | C50: 1423
A51: Total paid or credited to policyholders | B51: 37005 | C51: 47794
A52: Commissions | B52: 2148 | C52: 2107
A53: Operating and administrative expenses (note 27) | B53: 3249 | C53: 3175
A54: Premium taxes | B54: 474 | C54: 486
A55: Financing charges (note 16) | B55: 109 | C55: 110
A56: Amortization of finite life intangible assets (note 10) | B56: 168 | C56: 165
A57: Earnings before income taxes | B57: 3381 | C57: 3448
A58: Income taxes (note 26) | B58: 199 | C58: 274
... A63: Net earnings – common shareholder | B63: 2995 | C63: 2868
A66: Consolidated Balance Sheets | B66: 2022 | C66: 2021
A67: Assets
A68: Cash and cash equivalents (note 5) | B68: 3761 | C68: 3271
A69: Bonds (note 6) | B69: 87814 | C69: 101329
A70: Mortgage loans (note 6) | B70: 24012 | C70: 23113
A71: Stocks (note 6) | B71: 12663 | C71: 13252
A72: Investment properties (note 6) | B72: 8315 | C72: 7759
A73: Loans to policyholders | B73: 3660 | C73: 3480
B74: 140225 | C74: 152204
A75: Funds held by ceding insurers (note 7) | B75: 7041 | C75: 7555
A76: Reinsurance assets (note 13) | B76: 6877 | C76: 8794
A77: Goodwill (note 10) | B77: 6372 | C77: 6382
A78: Intangible assets (note 10) | B78: 2450 | C78: 2362
A79: Derivative financial instruments (note 28) | B79: 1120 | C79: 582
A80: Owner occupied properties (note 11) | B80: 532 | C80: 552
A81: Fixed assets (note 11) | B81: 257 | C81: 288
A82: Other assets (note 12) | B82: 2091 | C82: 1836
A83: Premiums in course of collection, accounts and interest receivable | B83: 4825 | C83: 4841
A84: Current income taxes | B84: 254 | C84: 242
A85: Deferred tax assets (note 26) | B85: 315 | C85: 266
A86: Investments on account of segregated fund policyholders (note 14) | B86: 221623 | C86: 240500
A87: Total assets | B87: 393982 | C87: 426404
A89: Liabilities
A90: Insurance contract liabilities (note 13) | B90: 134389 | C90: 148884
A91: Investment contract liabilities (note 13) | B91: 1568 | C91: 1646
A92: Debentures and other debt instruments (note 15) | B92: 747 | C92: 745
A93: Preferred shares (note 20) | B93: 1000 | C93: 1000
A94: Funds held under reinsurance contracts | B94: 1646 | C94: 2006
A95: Derivative financial instruments (note 28) | B95: 1575 | C95: 1005
A96: Accounts payable | B96: 2047 | C96: 1945
A97: Other liabilities (note 17) | B97: 2935 | C97: 3162
A98: Current income taxes | B98: 50 | C98: 160
A99: Deferred tax liabilities (note 26) | B99: 892 | C99: 922
A100: Investment and insurance contracts on account of segregated fund policyholders (note 14) | B100: 221623 | C100: 240500
A101: Total liabilities | B101: 368472 | C101: 401975
A102: Equity
A103: Participating account surplus (note 18) | B103: 3147 | C103: 3126
A104: Non-controlling interests (note 19) | B104: 51 | C104: 26
A105: Shareholders’ equity
A106: Share capital (note 20)
A107: Common shares | B107: 7884 | C107: 7884
A108: Accumulated surplus | B108: 14258 | C108: 13025
A109: Accumulated other comprehensive loss (note 24) | B109: -255 | C109: -51
A110: Contributed surplus | B110: 425 | C110: 419
A111: Total equity | B111: 25510 | C111: 24429
A112: Total liabilities and equity | B112: 393982 | C112: 426404
A115: Consolidated Statements of Changes in Equity | B115: Share capital | C115: Contributed surplus | D115: Accumulated surplus | E115: Accumulated other comprehensive loss comprehensive loss | F115: Total shareholders’ equity | G115: Non-controlling interests | H115: Participating account surplus | I115: Total equity
A116: Balance, beginning of year | B116: 7884 | C116: 419 | D116: 13025 | E116: -51 | F116: 21277 | G116: 26 | H116: 3126 | I116: 24429
A117: Net earnings | B117: – | C117: – | D117: 2995 | E117: – | F117: 2995 | G117: 3 | H117: 184 | I117: 3182
A118: Other comprehensive income (loss) | B118: – | C118: – | D118: – | E118: -204 | F118: -204 | G118: 1 | H118: -163 | I118: -366
B119: 7884 | C119: 419 | D119: 16020 | E119: -255 | F119: 24068 | G119: 30 | H119: 3147 | I119: 27245
A120: Dividends to common shareholder | B120: – | C120: – | D120: -1770 | E120: – | F120: -1770 | G120: – | H120: – | I120: -1770
A121: Share-based payments (note 22) | B121: – | C121: 6 | D121: – | E121: – | F121: 6 | G121: – | H121: – | I121: 6
...

Sheet CL Consolidated Summary
A1: Financial item (CAD $ millions) | B1: 2022 | C1: 2023 | D1: 2024 | E1: 2025
A2: Insurance revenue | B2: {=_xlfn.XLOOKUP(A2,CL2023_Consolidated_Statements_Of_Earnings[[#All],[Consolidated Statements of Earnings (in Canadian $ millions)]],CL2023_Consolidated_Statements_Of_Earnings[[#All],[2022]],"Not Found",0)} -> 19424 | C2: {=_xlfn.XLOOKUP(A2,CL2023_Consolidated_Statements_Of_Earnings[[#All],[Consolidated Statements of Earnings (in Canadian $ millions)]],CL2023_Consolidated_Statements_Of_Earnings[[#All],[2023]],"Not Found", 0)} -> 20188 | D2: {=_xlfn.XLOOKUP(A2,CL2024_Consolidated_Statement_Of_Earnings[[#All],[Consolidated Statements of Earnings (in Canadian $ millions)]],CL2024_Consolidated_Statement_Of_Earnings[[#All],[2024]],"Not Found", 0)} -> 21007 | E2: =_xlfn.XLOOKUP(A2,CL2025_Consolidated_Statements_Of_Earnings[Consolidated Statements Of Earnings (in Canadian $ Million)],CL2025_Consolidated_Statements_Of_Earnings[2025],"Not Found",0) -> 22131
A3: Insurance service expenses | B3: {=_xlfn.XLOOKUP(A3,CL2023_Consolidated_Statements_Of_Earnings[[#All],[Consolidated Statements of Earnings (in Canadian $ millions)]],CL2023_Consolidated_Statements_Of_Earnings[[#All],[2022]],"Not Found",0)} -> -15110 | C3: {=_xlfn.XLOOKUP(A3,CL2023_Consolidated_Statements_Of_Earnings[[#All],[Consolidated Statements of Earnings (in Canadian $ millions)]],CL2023_Consolidated_Statements_Of_Earnings[[#All],[2023]],"Not Found",0)} -> -15622 | D3: =_xlfn.XLOOKUP(A3,CL2024_Consolidated_Statement_Of_Earnings[Consolidated Statements of Earnings (in Canadian $ millions)],CL2024_Consolidated_Statement_Of_Earnings[2024],"Not Found",0) -> -16165 | E3: =_xlfn.XLOOKUP(A3,CL2025_Consolidated_Statements_Of_Earnings[Consolidated Statements Of Earnings (in Canadian $ Million)],CL2025_Consolidated_Statements_Of_Earnings[2025],"Not Found",0) -> -17002
A4: Insurance service result | B4: =SUM('CL 2023 (Original)'!C26:C28) -> 2766 | C4: =SUM('CL 2023 (Original)'!B26:B28) -> 3002 | D4: =SUM('CL 2024 (Original)'!B26:B28) -> 3258 | E4: =SUM('CL 2025 (Original)'!B26:B28) -> 3450
A5: Operating and administrative expenses | B5: {=_xlfn.XLOOKUP(A5,CL2023_Consolidated_Statements_Of_Earnings[[#All],[Consolidated Statements of Earnings (in Canadian $ millions)]],CL2023_Consolidated_Statements_Of_Earnings[[#All],[2022]],"Not Found",0)} -> -2221 | C5: {=_xlfn.XLOOKUP(A5,CL2023_Consolidated_Statements_Of_Earnings[[#All],[Consolidated Statements of Earnings (in Canadian $ millions)]],CL2023_Consolidated_Statements_Of_Earnings[[#All],[2023]],"Not Found",0)} -> -2635 | D5: {=_xlfn.XLOOKUP(A5,CL2024_Consolidated_Statement_Of_Earnings[[#All],[Consolidated Statements of Earnings (in Canadian $ millions)]],CL2024_Consolidated_Statement_Of_Earnings[[#All],[2024]],"Not Found",0)} -> -3088 | E5: {=_xlfn.XLOOKUP(A5,CL2025_Consolidated_Statements_Of_Earnings[[#All],[Consolidated Statements Of Earnings (in Canadian $ Million)]],CL2025_Consolidated_Statements_Of_Earnings[[#All],[2025]],"Not Found",0)} -> -3408
A6: Net earnings | B6: {=_xlfn.XLOOKUP(A6,CL2023_Consolidated_Statements_Of_Earnings[[#All],[Consolidated Statements of Earnings (in Canadian $ millions)]],CL2023_Consolidated_Statements_Of_Earnings[[#All],[2022]],"Not Found",0)} -> 3286 | C6: {=_xlfn.XLOOKUP(A6,CL2023_Consolidated_Statements_Of_Earnings[[#All],[Consolidated Statements of Earnings (in Canadian $ millions)]],CL2023_Consolidated_Statements_Of_Earnings[[#All],[2023]],"Not Found",0)} -> 2418 | D6: {=_xlfn.XLOOKUP(A6,CL2024_Consolidated_Statement_Of_Earnings[[#All],[Consolidated Statements of Earnings (in Canadian $ millions)]],CL2024_Consolidated_Statement_Of_Earnings[[#All],[2024]],"Not Found",0)} -> 3247 | E6: {=_xlfn.XLOOKUP(A6,CL2025_Consolidated_Statements_Of_Earnings[[#All],[Consolidated Statements Of Earnings (in Canadian $ Million)]],CL2025_Consolidated_Statements_Of_Earnings[[#All],[2025]],"Not Found",0)} -> 2766
A7: Total assets | B7: {=_xlfn.XLOOKUP(A7,CL2023_Consolidated_Balance_Sheets[[#All],[Consolidated Balance Sheets (in Canadian $ millions)]],CL2023_Consolidated_Balance_Sheets[[#All],[2022]],"Not Found", 0)} -> 378654 | C7: {=_xlfn.XLOOKUP(A7,CL2023_Consolidated_Balance_Sheets[[#All],[Consolidated Balance Sheets (in Canadian $ millions)]],CL2023_Consolidated_Balance_Sheets[[#All],[2023]],"Not Found",0)} -> 410616 | D7: {=_xlfn.XLOOKUP(A7,CL2024_Consolidated_Balance_Sheet[[#All],[Consolidated Balance Sheet (in Canadian $ millions)]],CL2024_Consolidated_Balance_Sheet[[#All],[2024]],"Not Found",0)} -> 461204 | E7: {=_xlfn.XLOOKUP(A7,CL2025_Consolidated_Balance_Sheet[[#All],[Consolidated Balance Sheet (in Canadian $ Million)]],CL2025_Consolidated_Balance_Sheet[[#All],[2025]],"Not Found",0)} -> 505652
A8: Total liabilities | B8: {=_xlfn.XLOOKUP(A8,CL2023_Consolidated_Balance_Sheets[[#All],[Consolidated Balance Sheets (in Canadian $ millions)]],CL2023_Consolidated_Balance_Sheets[[#All],[2022]],"Not Found",0)} -> 355866 | C8: {=_xlfn.XLOOKUP(A8,CL2023_Consolidated_Balance_Sheets[[#All],[Consolidated Balance Sheets (in Canadian $ millions)]],CL2023_Consolidated_Balance_Sheets[[#All],[2023]],"Not Found",0)} -> 387943 | D8: {=_xlfn.XLOOKUP(A8,CL2024_Consolidated_Balance_Sheet[[#All],[Consolidated Balance Sheet (in Canadian $ millions)]],CL2024_Consolidated_Balance_Sheet[[#All],[2024]],"Not Found",0)} -> 437242 | E8: {=_xlfn.XLOOKUP(A8,CL2025_Consolidated_Balance_Sheet[[#All],[Consolidated Balance Sheet (in Canadian $ Million)]],CL2025_Consolidated_Balance_Sheet[[#All],[2025]],"Not Found",0)} -> 481632
A9: Shareholders’ equity | B9: {=_xlfn.XLOOKUP(A9,CL2023_Financial_Highlights[[#All],[Financial Highlights (unaudited) (in Canadian $ millions)]],CL2023_Financial_Highlights[[#All],[2022]],"Not Found",0)} -> 20004 | C9: {=_xlfn.XLOOKUP(A9,CL2023_Financial_Highlights[[#All],[Financial Highlights (unaudited) (in Canadian $ millions)]],CL2023_Financial_Highlights[[#All],[2023]],"Not Found",0)} -> 19813 | D9: {=_xlfn.XLOOKUP(A9,CL2024_Financial_Highlights[[#All],[Financial Highlights (in Canadian $ millions)]],CL2024_Financial_Highlights[[#All],[2024]],"Not Found",0)} -> 20909 | E9: {=_xlfn.XLOOKUP(A9,CL2025_Financial_Highlights[[#All],[Financial Highlights (Unaudited) (in Canadian $ Million)]],CL2025_Financial_Highlights[[#All],[2025]],"Not Found",0)} -> 20938
A10: Cash and cash equivalents | B10: {=_xlfn.XLOOKUP(A10,CL2023_Consolidated_Balance_Sheets[[#All],[Consolidated Balance Sheets (in Canadian $ millions)]],CL2023_Consolidated_Balance_Sheets[[#All],[2022]],"Not Found",0)} -> 3761 | C10: {=_xlfn.XLOOKUP(A10,CL2023_Consolidated_Balance_Sheets[[#All],[Consolidated Balance Sheets (in Canadian $ millions)]],CL2023_Consolidated_Balance_Sheets[[#All],[2023]],"Not Found",0)} -> 3944 | D10: {=_xlfn.XLOOKUP(A10,CL2024_Consolidated_Balance_Sheet[[#All],[Consolidated Balance Sheet (in Canadian $ millions)]],CL2024_Consolidated_Balance_Sheet[[#All],[2024]],"Not Found",0)} -> 4522 | E10: {=_xlfn.XLOOKUP(A10,CL2025_Consolidated_Balance_Sheet[[#All],[Consolidated Balance Sheet (in Canadian $ Million)]],CL2025_Consolidated_Balance_Sheet[[#All],[2025]],"Not Found",0)} -> 4679
A11: Debentures and other debt instruments | B11: {=_xlfn.XLOOKUP(A11,CL2023_Consolidated_Balance_Sheets[[#All],[Consolidated Balance Sheets (in Canadian $ millions)]],CL2023_Consolidated_Balance_Sheets[[#All],[2022]],"Not Found",0)} -> 747 | C11: {=_xlfn.XLOOKUP(A11,CL2023_Consolidated_Balance_Sheets[[#All],[Consolidated Balance Sheets (in Canadian $ millions)]],CL2023_Consolidated_Balance_Sheets[[#All],[2023]],"Not Found",0)} -> 748 | D11: {=_xlfn.XLOOKUP(A11,CL2024_Consolidated_Balance_Sheet[[#All],[Consolidated Balance Sheet (in Canadian $ millions)]],CL2024_Consolidated_Balance_Sheet[[#All],[2024]],"Not Found",0)} -> 807 | E11: {=_xlfn.XLOOKUP(A11,CL2025_Consolidated_Balance_Sheet[[#All],[Consolidated Balance Sheet (in Canadian $ Million)]],CL2025_Consolidated_Balance_Sheet[[#All],[2025]],"Not Found",0)} -> 827
A12: Operating cash flow | B12: ='CL 2023 (Original)'!C137 -> 2343 | C12: ='CL 2023 (Original)'!B137 -> 3836 | D12: ='CL 2024 (Original)'!B132 -> 3347 | E12: ='CL 2025 (Original)'!B135 -> 3251
A13: Total contractual service margin (net of reinsurance held) | B13: {=_xlfn.XLOOKUP(A13,CL2023_Financial_Highlights[[#All],[Financial Highlights (unaudited) (in Canadian $ millions)]],CL2023_Financial_Highlights[[#All],[2022]],"Not Found",0)} -> 12496 | C13: {=_xlfn.XLOOKUP(A13,CL2023_Financial_Highlights[[#All],[Financial Highlights (unaudited) (in Canadian $ millions)]],CL2023_Financial_Highlights[[#All],[2023]],"Not Found",0)} -> 12458 | D13: {=_xlfn.XLOOKUP(A13,CL2024_Financial_Highlights[[#All],[Financial Highlights (in Canadian $ millions)]],CL2024_Financial_Highlights[[#All],[2024]],"Not Found",0)} -> 13243 | E13: {=_xlfn.XLOOKUP(A13,CL2025_Financial_Highlights[[#All],[Financial Highlights (Unaudited) (in Canadian $ Million)]],CL2025_Financial_Highlights[[#All],[2025]],"Not Found",0)} -> 13494
A14: Shareholders’ equity | B14: {=_xlfn.XLOOKUP(A14,CL2023_Financial_Highlights[[#All],[Financial Highlights (unaudited) (in Canadian $ millions)]],CL2023_Financial_Highlights[[#All],[2022]],"Not Found",0)} -> 20004 | C14: {=_xlfn.XLOOKUP(A14,CL2023_Financial_Highlights[[#All],[Financial Highlights (unaudited) (in Canadian $ millions)]],CL2023_Financial_Highlights[[#All],[2023]],"Not Found",0)} -> 19813 | D14: {=_xlfn.XLOOKUP(A14,CL2024_Financial_Highlights[[#All],[Financial Highlights (in Canadian $ millions)]],CL2024_Financial_Highlights[[#All],[2024]],"Not Found",0)} -> 20909 | E14: {=_xlfn.XLOOKUP(A14,CL2025_Financial_Highlights[[#All],[Financial Highlights (Unaudited) (in Canadian $ Million)]],CL2025_Financial_Highlights[[#All],[2025]],"Not Found",0)} -> 20938
A15: Total equity | B15: {=_xlfn.XLOOKUP(A15,CL2023_Financial_Highlights[[#All],[Financial Highlights (unaudited) (in Canadian $ millions)]],CL2023_Financial_Highlights[[#All],[2022]],"Not Found",0)} -> 22788 | C15: {=_xlfn.XLOOKUP(A15,CL2023_Financial_Highlights[[#All],[Financial Highlights (unaudited) (in Canadian $ millions)]],CL2023_Financial_Highlights[[#All],[2023]],"Not Found",0)} -> 22673 | D15: {=_xlfn.XLOOKUP(A15,CL2024_Financial_Highlights[[#All],[Financial Highlights (in Canadian $ millions)]],CL2024_Financial_Highlights[[#All],[2024]],"Not Found",0)} -> 23962 | E15: {=_xlfn.XLOOKUP(A15,CL2025_Financial_Highlights[[#All],[Financial Highlights (Unaudited) (in Canadian $ Million)]],CL2025_Financial_Highlights[[#All],[2025]],"Not Found",0)} -> 24020
A16: Dividends paid on common shares | B16: {=_xlfn.XLOOKUP(A16,CL2023_Consolidated_Statements_Of_Cash_Flows[[#All],[Consolidated Statements of Cash Flows (in Canadian $ millions)]],CL2023_Consolidated_Statements_Of_Cash_Flows[[#All],[2022]],"Not Found",0)} -> -1770 | C16: {=_xlfn.XLOOKUP(A16,CL2023_Consolidated_Statements_Of_Cash_Flows[[#All],[Consolidated Statements of Cash Flows (in Canadian $ millions)]],CL2023_Consolidated_Statements_Of_Cash_Flows[[#All],[2023]],"Not Found",0)} -> -2934 | D16: {=_xlfn.XLOOKUP(A16,CL2024_Consolidated_Statements_Of_Cash_Flow[[#All],[Consolidated Statements of Cash Flow (in Canadian $ millions)]],CL2024_Consolidated_Statements_Of_Cash_Flow[[#All],[2024]],"Not Found",0)} -> -2838 | E16: {=_xlfn.XLOOKUP(A16,CL2025_Consolidated_Statements_Of_Cash_Flow[[#All],[Consolidated Statements of Cash Flow]],CL2025_Consolidated_Statements_Of_Cash_Flow[[#All],[2025]],"Not Found",0)} -> -3150
A17: LICAT Ratio | B17: {=_xlfn.XLOOKUP(A17,CL2023_Financial_Highlights[[#All],[Financial Highlights (unaudited) (in Canadian $ millions)]],CL2023_Financial_Highlights[[#All],[2022]],"Not Found",0)} -> 1.2 | C17: {=_xlfn.XLOOKUP(A17,CL2023_Financial_Highlights[[#All],[Financial Highlights (unaudited) (in Canadian $ millions)]],CL2023_Financial_Highlights[[#All],[2023]],"Not Found",0)} -> 1.28 | D17: {=_xlfn.XLOOKUP(A17,CL2024_Financial_Highlights[[#All],[Financial Highlights (in Canadian $ millions)]],CL2024_Financial_Highlights[[#All],[2024]],"Not Found",0)} -> 1.3 | E17: {=_xlfn.XLOOKUP(A17,CL2025_Financial_Highlights[[#All],[Financial Highlights (Unaudited) (in Canadian $ Million)]],CL2025_Financial_Highlights[[#All],[2025]],"Not Found",0)} -> 1.28
